antgent/__init__.py
antgent/clients.py
antgent/config.py
antgent/init.py
antgent/s3.py
antgent/version.py
antgent/agents/__init__.py
antgent/agents/base.py
antgent/agents/summarizer/models.py
antgent/agents/summarizer/summary.py
antgent/agents/summarizer/summary_judge.py
antgent/cmd/__init__.py
antgent/cmd/main.py
antgent/cmd/server.py
antgent/cmd/tiktoken.py
antgent/files/DejaVuSans.ttf
antgent/models/__init__.py
antgent/models/agent.py
antgent/models/job.py
antgent/models/message.py
antgent/models/visibility.py
antgent/server/__init__.py
antgent/server/server.py
antgent/server/api/__init__.py
antgent/server/api/job_info.py
antgent/temporal/__init__.py
antgent/temporal/activities.py
antgent/temporal/client.py
antgent/temporal/workflows/__init__.py
antgent/temporal/workflows/echo.py
antgent/utils/__init__.py
antgent/utils/aliases.py
antgent/utils/csv.py
antgent/utils/doc.py
antgent/utils/graph.py
antgent/utils/importpy.py
antgent/utils/json.py
antgent/utils/pdf.py
antgent/workflows/__init__.py
antgent/workflows/base.py
antgent/workflows/summarizer.py
antgent-0.3.1.dist-info/METADATA
antgent-0.3.1.dist-info/WHEEL
antgent-0.3.1.dist-info/licenses/LICENSE
antgent-0.3.1.dist-info/RECORD
